MANIFEST.in
README.md
setup.py
title_graph/__init__.py
title_graph/title_graph.py
title_graph.egg-info/PKG-INFO
title_graph.egg-info/SOURCES.txt
title_graph.egg-info/dependency_links.txt
title_graph.egg-info/requires.txt
title_graph.egg-info/top_level.txt
title_graph/data/gram_counts.pkl
title_graph/data/graph.pkl
title_graph/data/kp.pkl
title_graph/data/title_model.kv