Metadata-Version: 1.2
Name: title-graph
Version: 0.0.5
Summary: Resolving Messy Job Titles
Home-page: https://github.com/estasney/TitleGraph
Author: Eric Stasney
Author-email: 16440579+estasney@users.noreply.github.com
License: MIT
Platform: UNKNOWN
Classifier: License :: OSI Approved :: MIT License
Classifier: Programming Language :: Python
Classifier: Programming Language :: Python :: 3
Classifier: Programming Language :: Python :: 3.6
Requires-Python: >=3.6.0
